prefect_discord/__init__.py
prefect_discord/_version.py
prefect_discord/notifications.py
prefect_2_discord-0.1.1.dist-info/LICENSE
prefect_2_discord-0.1.1.dist-info/METADATA
prefect_2_discord-0.1.1.dist-info/WHEEL
prefect_2_discord-0.1.1.dist-info/entry_points.txt
prefect_2_discord-0.1.1.dist-info/top_level.txt
prefect_2_discord-0.1.1.dist-info/RECORD
